likeprocessing/affichage.py
likeprocessing/bloc2D.py
likeprocessing/error.png
likeprocessing/exceptions.py
likeprocessing/formes.py
likeprocessing/images/image1.png
likeprocessing/images/image10.png
likeprocessing/images/image2.png
likeprocessing/images/image3.png
likeprocessing/images/image4.png
likeprocessing/images/image5.png
likeprocessing/images/image6.png
likeprocessing/images/image7.png
likeprocessing/images/image8.png
likeprocessing/images/image9.png
likeprocessing/images.py
likeprocessing/info.png
likeprocessing/jauge.py
likeprocessing/list_tools.py
likeprocessing/print_vars.py
likeprocessing/processing.py
likeprocessing/pyDialog.py
likeprocessing/pygame_textinput.py
likeprocessing/question.png
likeprocessing/README.md
likeprocessing/tempos.py
likeprocessing/texte.py
likeprocessing/tor.py
likeprocessing/transformation.py
likeprocessing/trigo.py
likeprocessing/warning.png
likeprocessing-0.1.7.5.6.dist-info/WHEEL
likeprocessing-0.1.7.5.6.dist-info/METADATA
likeprocessing-0.1.7.5.6.dist-info/RECORD
