Metadata-Version: 2.1
Name: likeprocessing
Version: 0.1.7.5.6
Summary: Like processing library with pygame
Author: Pierre Lemaitre
Author-email: oultetman@sfr.fr
Requires-Python: >=3.9,<4.0
Classifier: Programming Language :: Python :: 3
Classifier: Programming Language :: Python :: 3.10
Classifier: Programming Language :: Python :: 3.9
Requires-Dist: pygame (>=2.1.2,<3.0.0)
Requires-Dist: pyperclip (>=1.8.2,<2.0.0)
